{
    "codec-support-test" : {
        "CanPlay audio/mp4 aac" : ["passed"],
        "CanPlay audio/mp4 ac3" : ["passed"],
        "CanPlay audio/mp4 eac3" : ["passed"],
        "CanPlay audio/mp4 mp3" : ["passed"],
        "CanPlay audio/webm opus" : ["passed"],
        "CanPlay video/mp2t avc" : ["failed"],
        "CanPlay video/mp2t mpeg2" : ["failed"],
        "CanPlay video/mp4 avc" : ["passed"],
        "CanPlay video/mp4 hevc" : ["passed"],
        "CanPlay video/webm vp9" : ["passed"],
        "CanPlay video/x-matroska avc" : ["passed"],
        "CanPlay video/x-matroska hevc" : ["passed"],
        "IsTypeSupported audio/mp4 aac" : ["passed"],
        "IsTypeSupported audio/mp4 ac3" : ["passed"],
        "IsTypeSupported audio/mp4 eac3" : ["passed"],
        "IsTypeSupported audio/mp4 mp3" : ["passed"],
        "IsTypeSupported audio/webm opus" : ["passed"],
        "IsTypeSupported video/mp2t avc" : ["skipped"],
        "IsTypeSupported video/mp2t mpeg2" : ["skipped"],
        "IsTypeSupported video/mp4 avc" : ["passed"],
        "IsTypeSupported video/mp4 hevc" : ["passed"],
        "IsTypeSupported video/webm vp9" : ["passed"],
        "IsTypeSupported video/x-matroska avc" : ["skipped"],
        "IsTypeSupported video/x-matroska hevc" : ["skipped"]
    },
    "dash-dashjs-test" : {
        "DASH_CMAF_AVC_AC3 Pause" : ["passed"],
        "DASH_CMAF_AVC_AC3 Playback" : ["passed"],
        "DASH_CMAF_AVC_AC3 Seek" : ["failed"],
        "DASH_CMAF_AVC_MP3 Pause" : ["passed"],
        "DASH_CMAF_AVC_MP3 Playback" : ["passed"],
        "DASH_CMAF_AVC_MP3 Seek" : ["failed", "passed"],
        "DASH_CMAF_AVC_MP3_VTT Subtitles" : ["passed"],
        "DASH_CMAF_HEVC_AAC Pause" : ["passed"],
        "DASH_CMAF_HEVC_AAC Playback" : ["passed"],
        "DASH_CMAF_HEVC_AAC Seek" : ["failed", "passed"],
        "DASH_CMAF_HEVC_EAC3 Pause" : ["passed"],
        "DASH_CMAF_HEVC_EAC3 Playback" : ["passed"],
        "DASH_CMAF_HEVC_EAC3 Seek" : ["failed", "passed"],
        "DASH_DYNAMIC Pause" : ["passed"],
        "DASH_DYNAMIC Playback" : ["passed"],
        "DASH_DYNAMIC Seek" : ["failed"],
        "DASH_FMP4_AVC_AAC Pause" : ["passed"],
        "DASH_FMP4_AVC_AAC Playback" : ["passed"],
        "DASH_FMP4_AVC_AAC Seek" : ["failed"],
        "DASH_FMP4_AVC_AAC_TTML Subtitles" : ["passed"],
        "DASH_FMP4_AVC_AC3 Pause" : ["passed"],
        "DASH_FMP4_AVC_AC3 Playback" : ["passed"],
        "DASH_FMP4_AVC_AC3 Seek" : ["failed"],
        "DASH_FMP4_HEVC_EAC3 Pause" : ["passed"],
        "DASH_FMP4_HEVC_EAC3 Playback" : ["passed"],
        "DASH_FMP4_HEVC_EAC3 Seek" : ["passed"],
        "DASH_FMP4_MP3 Pause" : ["passed"],
        "DASH_FMP4_MP3 Playback" : ["passed"],
        "DASH_FMP4_MP3 Seek" : ["passed"],
        "DASH_FMP4_MPEG2_MP3 Pause" : ["passed"],
        "DASH_FMP4_MPEG2_MP3 Playback" : ["passed"],
        "DASH_FMP4_MPEG2_MP3 Seek" : ["passed"],
        "DASH_MULTIAUDIO AudioTracks" : ["passed"],
        "DASH_MULTIPERIOD Pause" : ["passed"],
        "DASH_MULTIPERIOD Playback" : ["passed"],
        "DASH_MULTIPERIOD Seek" : ["skipped"],
        "DASH_PLAYREADY_2_0 Pause" : ["failed"],
        "DASH_PLAYREADY_2_0 Playback" : ["failed"],
        "DASH_PLAYREADY_2_0 Seek" : ["failed"],
        "DASH_WEBM_VP9_OPUS Pause" : ["passed"],
        "DASH_WEBM_VP9_OPUS Playback" : ["passed"],
        "DASH_WEBM_VP9_OPUS Seek" : ["passed"],
        "DASH_WEBM_VP9_OPUS_VTT Subtitles" : ["failed", "passed"]
    },
    "dash-html5-test" : {
        "DASH_CMAF_AVC_AC3 Pause" : ["failed"],
        "DASH_CMAF_AVC_AC3 Playback" : ["failed"],
        "DASH_CMAF_AVC_AC3 Seek" : ["failed"],
        "DASH_CMAF_AVC_MP3 Pause" : ["failed"],
        "DASH_CMAF_AVC_MP3 Playback" : ["failed"],
        "DASH_CMAF_AVC_MP3 Seek" : ["failed"],
        "DASH_CMAF_AVC_MP3_VTT Subtitles" : ["skipped"],
        "DASH_CMAF_HEVC_AAC Pause" : ["failed"],
        "DASH_CMAF_HEVC_AAC Playback" : ["failed"],
        "DASH_CMAF_HEVC_AAC Seek" : ["failed"],
        "DASH_CMAF_HEVC_EAC3 Pause" : ["failed"],
        "DASH_CMAF_HEVC_EAC3 Playback" : ["failed"],
        "DASH_CMAF_HEVC_EAC3 Seek" : ["failed"],
        "DASH_DYNAMIC Pause" : ["skipped"],
        "DASH_DYNAMIC Playback" : ["skipped"],
        "DASH_DYNAMIC Seek" : ["skipped"],
        "DASH_FMP4_AVC_AAC Pause" : ["failed"],
        "DASH_FMP4_AVC_AAC Playback" : ["failed"],
        "DASH_FMP4_AVC_AAC Seek" : ["failed"],
        "DASH_FMP4_AVC_AAC_TTML Subtitles" : ["skipped"],
        "DASH_FMP4_AVC_AC3 Pause" : ["failed"],
        "DASH_FMP4_AVC_AC3 Playback" : ["failed"],
        "DASH_FMP4_AVC_AC3 Seek" : ["failed"],
        "DASH_FMP4_HEVC_EAC3 Pause" : ["skipped"],
        "DASH_FMP4_HEVC_EAC3 Playback" : ["failed"],
        "DASH_FMP4_HEVC_EAC3 Seek" : ["failed"],
        "DASH_FMP4_MP3 Pause" : ["failed"],
        "DASH_FMP4_MP3 Playback" : ["failed"],
        "DASH_FMP4_MP3 Seek" : ["failed"],
        "DASH_FMP4_MPEG2_MP3 Pause" : ["failed"],
        "DASH_FMP4_MPEG2_MP3 Playback" : ["failed"],
        "DASH_FMP4_MPEG2_MP3 Seek" : ["failed"],
        "DASH_MULTIAUDIO AudioTracks" : ["failed"],
        "DASH_MULTIPERIOD Pause" : ["skipped"],
        "DASH_MULTIPERIOD Playback" : ["skipped"],
        "DASH_MULTIPERIOD Seek" : ["skipped"],
        "DASH_WEBM_VP9_OPUS Pause" : ["skipped"],
        "DASH_WEBM_VP9_OPUS Playback" : ["skipped"],
        "DASH_WEBM_VP9_OPUS Seek" : ["skipped"],
        "DASH_WEBM_VP9_OPUS_VTT Subtitles" : ["skipped"]
    },
    "dash-shaka-test" : {
        "DASH_CMAF_AVC_AC3 Pause" : ["passed"],
        "DASH_CMAF_AVC_AC3 Playback" : ["passed"],
        "DASH_CMAF_AVC_AC3 Seek" : ["failed", "passed"],
        "DASH_CMAF_AVC_MP3 Pause" : ["passed"],
        "DASH_CMAF_AVC_MP3 Playback" : ["passed"],
        "DASH_CMAF_AVC_MP3 Seek" : ["failed", "passed"],
        "DASH_CMAF_AVC_MP3_VTT Subtitles" : ["passed"],
        "DASH_CMAF_HEVC_AAC Pause" : ["passed"],
        "DASH_CMAF_HEVC_AAC Playback" : ["passed"],
        "DASH_CMAF_HEVC_AAC Seek" : ["failed", "passed"],
        "DASH_CMAF_HEVC_EAC3 Pause" : ["failed"],
        "DASH_CMAF_HEVC_EAC3 Playback" : ["failed"],
        "DASH_CMAF_HEVC_EAC3 Seek" : ["failed"],
        "DASH_DYNAMIC Pause" : ["passed"],
        "DASH_DYNAMIC Playback" : ["passed"],
        "DASH_DYNAMIC Seek" : ["failed", "passed"],
        "DASH_FMP4_AVC_AAC Pause" : ["passed"],
        "DASH_FMP4_AVC_AAC Playback" : ["passed"],
        "DASH_FMP4_AVC_AAC Seek" : ["failed"],
        "DASH_FMP4_AVC_AAC_TTML Subtitles" : ["passed"],
        "DASH_FMP4_AVC_AC3 Pause" : ["passed"],
        "DASH_FMP4_AVC_AC3 Playback" : ["passed"],
        "DASH_FMP4_AVC_AC3 Seek" : ["failed"],
        "DASH_FMP4_HEVC_EAC3 Pause" : ["failed"],
        "DASH_FMP4_HEVC_EAC3 Playback" : ["failed"],
        "DASH_FMP4_HEVC_EAC3 Seek" : ["failed"],
        "DASH_FMP4_MP3 Pause" : ["passed"],
        "DASH_FMP4_MP3 Playback" : ["passed"],
        "DASH_FMP4_MP3 Seek" : ["passed"],
        "DASH_FMP4_MPEG2_MP3 Pause" : ["passed"],
        "DASH_FMP4_MPEG2_MP3 Playback" : ["passed"],
        "DASH_FMP4_MPEG2_MP3 Seek" : ["failed", "passed"],
        "DASH_MULTIAUDIO AudioTracks" : ["skipped"],
        "DASH_MULTIPERIOD Pause" : ["passed"],
        "DASH_MULTIPERIOD Playback" : ["passed"],
        "DASH_MULTIPERIOD Seek" : ["skipped"],
        "DASH_PLAYREADY_2_0 Pause" : ["failed"],
        "DASH_PLAYREADY_2_0 Playback" : ["failed"],
        "DASH_PLAYREADY_2_0 Seek" : ["failed"],
        "DASH_WEBM_VP9_OPUS Pause" : ["passed"],
        "DASH_WEBM_VP9_OPUS Playback" : ["passed"],
        "DASH_WEBM_VP9_OPUS Seek" : ["passed"],
        "DASH_WEBM_VP9_OPUS_VTT Subtitles" : ["passed"]
    },
    "hls-hlsjs-test" : {
        "HLS_CMAF_AVC_AAC Pause" : ["passed"],
        "HLS_CMAF_AVC_AAC Playback" : ["passed"],
        "HLS_CMAF_AVC_AAC Seek" : ["failed"],
        "HLS_CMAF_AVC_AC3 Pause" : ["passed"],
        "HLS_CMAF_AVC_AC3 Playback" : ["passed"],
        "HLS_CMAF_AVC_AC3 Seek" : ["failed", "passed"],
        "HLS_CMAF_AVC_MP3 Pause" : ["passed"],
        "HLS_CMAF_AVC_MP3 Playback" : ["passed"],
        "HLS_CMAF_AVC_MP3 Seek" : ["failed"],
        "HLS_CMAF_HEVC_AAC Pause" : ["passed"],
        "HLS_CMAF_HEVC_AAC Playback" : ["passed"],
        "HLS_CMAF_HEVC_AAC Seek" : ["passed"],
        "HLS_CMAF_HEVC_EAC3 Pause" : ["failed"],
        "HLS_CMAF_HEVC_EAC3 Playback" : ["failed"],
        "HLS_CMAF_HEVC_EAC3 Seek" : ["failed"],
        "HLS_FMP4_AVC_AAC_VTT Subtitles" : ["passed"],
        "HLS_FMP4_AVC_EAC3 Pause" : ["failed"],
        "HLS_FMP4_AVC_EAC3 Playback" : ["failed"],
        "HLS_FMP4_AVC_EAC3 Seek" : ["failed"],
        "HLS_FMP4_HEVC_AC3 Pause" : ["passed"],
        "HLS_FMP4_HEVC_AC3 Playback" : ["passed"],
        "HLS_FMP4_HEVC_AC3 Seek" : ["passed"],
        "HLS_FMP4_MP3 Pause" : ["passed"],
        "HLS_FMP4_MP3 Playback" : ["passed"],
        "HLS_FMP4_MP3 Seek" : ["passed"],
        "HLS_FMP4_MULTIAUDIO AudioTracks" : ["passed"],
        "HLS_MP2TS_AVC_AAC Pause" : ["passed"],
        "HLS_MP2TS_AVC_AAC Playback" : ["passed"],
        "HLS_MP2TS_AVC_AAC Seek" : ["failed"]
    },
    "hls-shaka-test" : {
        "HLS_CMAF_AVC_AAC Pause" : ["failed"],
        "HLS_CMAF_AVC_AAC Playback" : ["failed"],
        "HLS_CMAF_AVC_AAC Seek" : ["failed"],
        "HLS_CMAF_AVC_AC3 Pause" : ["passed"],
        "HLS_CMAF_AVC_AC3 Playback" : ["passed"],
        "HLS_CMAF_AVC_AC3 Seek" : ["failed", "passed"],
        "HLS_CMAF_AVC_MP3 Pause" : ["passed"],
        "HLS_CMAF_AVC_MP3 Playback" : ["passed"],
        "HLS_CMAF_AVC_MP3 Seek" : ["failed", "passed"],
        "HLS_CMAF_HEVC_AAC Pause" : ["passed"],
        "HLS_CMAF_HEVC_AAC Playback" : ["passed"],
        "HLS_CMAF_HEVC_AAC Seek" : ["failed", "passed"],
        "HLS_CMAF_HEVC_EAC3 Pause" : ["failed"],
        "HLS_CMAF_HEVC_EAC3 Playback" : ["failed"],
        "HLS_CMAF_HEVC_EAC3 Seek" : ["failed"],
        "HLS_FMP4_AVC_AAC_VTT Subtitles" : ["passed"],
        "HLS_FMP4_AVC_EAC3 Pause" : ["failed"],
        "HLS_FMP4_AVC_EAC3 Playback" : ["failed"],
        "HLS_FMP4_AVC_EAC3 Seek" : ["failed"],
        "HLS_FMP4_HEVC_AC3 Pause" : ["passed"],
        "HLS_FMP4_HEVC_AC3 Playback" : ["passed"],
        "HLS_FMP4_HEVC_AC3 Seek" : ["failed", "passed"],
        "HLS_FMP4_MP3 Pause" : ["passed"],
        "HLS_FMP4_MP3 Playback" : ["passed"],
        "HLS_FMP4_MP3 Seek" : ["passed"],
        "HLS_FMP4_MULTIAUDIO AudioTracks" : ["failed"],
        "HLS_MP2TS_AVC_AAC Pause" : ["failed", "passed"],
        "HLS_MP2TS_AVC_AAC Playback" : ["passed"],
        "HLS_MP2TS_AVC_AAC Seek" : ["failed", "passed"]
    },
    "hss-dashjs-test" : {
        "HSS_FMP4_AVC_AAC_VTT Pause" : ["failed"],
        "HSS_FMP4_AVC_AAC_VTT Playback" : ["failed"],
        "HSS_FMP4_AVC_AAC_VTT Seek" : ["failed"],
        "HSS_PLAYREADY_2_0 Pause" : ["failed"],
        "HSS_PLAYREADY_2_0 Playback" : ["failed"],
        "HSS_PLAYREADY_2_0 Seek" : ["failed"]
    },
    "hss-html5-test" : {
        "HSS_FMP4_AVC_AAC_VTT Pause" : ["failed"],
        "HSS_FMP4_AVC_AAC_VTT Playback" : ["failed"],
        "HSS_FMP4_AVC_AAC_VTT Seek" : ["failed"],
        "HSS_FMP4_AVC_AAC_VTT Subtitles" : ["failed"]
    },
    "progressive-html5-test" : {
        "PROG_MKV_AVC Pause" : ["passed"],
        "PROG_MKV_AVC Playback" : ["passed"],
        "PROG_MKV_AVC Seek" : ["passed"],
        "PROG_MKV_AVC_AAC_VTT Subtitles" : ["passed"],
        "PROG_MKV_AVC_AC3 Pause" : ["passed"],
        "PROG_MKV_AVC_AC3 Playback" : ["passed"],
        "PROG_MKV_AVC_AC3 Seek" : ["passed"],
        "PROG_MKV_AVC_EAC3 Pause" : ["passed"],
        "PROG_MKV_AVC_EAC3 Playback" : ["passed"],
        "PROG_MKV_AVC_EAC3 Seek" : ["passed"],
        "PROG_MKV_AVC_MP3 Pause" : ["passed"],
        "PROG_MKV_AVC_MP3 Playback" : ["passed"],
        "PROG_MKV_AVC_MP3 Seek" : ["passed"],
        "PROG_MKV_EAC3 Pause" : ["skipped"],
        "PROG_MKV_EAC3 Playback" : ["failed"],
        "PROG_MKV_EAC3 Seek" : ["skipped"],
        "PROG_MKV_HEVC_AAC Pause" : ["passed"],
        "PROG_MKV_HEVC_AAC Playback" : ["passed"],
        "PROG_MKV_HEVC_AAC Seek" : ["passed"],
        "PROG_MKV_MPEG2V_AAC Pause" : ["passed"],
        "PROG_MKV_MPEG2V_AAC Playback" : ["passed"],
        "PROG_MKV_MPEG2V_AAC Seek" : ["passed"],
        "PROG_MKV_VP9_AAC Pause" : ["passed"],
        "PROG_MKV_VP9_AAC Playback" : ["passed"],
        "PROG_MKV_VP9_AAC Seek" : ["passed"],
        "PROG_MP3_MP3 Pause" : ["passed"],
        "PROG_MP3_MP3 Playback" : ["passed"],
        "PROG_MP3_MP3 Seek" : ["passed"],
        "PROG_MP4_AVC Pause" : ["failed"],
        "PROG_MP4_AVC Playback" : ["failed"],
        "PROG_MP4_AVC Seek" : ["failed"],
        "PROG_MP4_AVC_AAC_VTT Subtitles" : ["passed"],
        "PROG_MP4_AVC_AC3 Pause" : ["passed"],
        "PROG_MP4_AVC_AC3 Playback" : ["passed"],
        "PROG_MP4_AVC_AC3 Seek" : ["passed"],
        "PROG_MP4_AVC_EAC3 Pause" : ["passed"],
        "PROG_MP4_AVC_EAC3 Playback" : ["passed"],
        "PROG_MP4_AVC_EAC3 Seek" : ["passed"],
        "PROG_MP4_AVC_MP3 Pause" : ["passed"],
        "PROG_MP4_AVC_MP3 Playback" : ["passed"],
        "PROG_MP4_AVC_MP3 Seek" : ["passed"],
        "PROG_MP4_EAC3 Pause" : ["failed"],
        "PROG_MP4_EAC3 Playback" : ["failed"],
        "PROG_MP4_EAC3 Seek" : ["failed"],
        "PROG_MP4_HEVC_AAC Pause" : ["passed"],
        "PROG_MP4_HEVC_AAC Playback" : ["passed"],
        "PROG_MP4_HEVC_AAC Seek" : ["failed", "passed"],
        "PROG_MP4_MPEG2V_AAC Pause" : ["passed"],
        "PROG_MP4_MPEG2V_AAC Playback" : ["passed"],
        "PROG_MP4_MPEG2V_AAC Seek" : ["passed"],
        "PROG_MP4_VP9_AAC Pause" : ["passed"],
        "PROG_MP4_VP9_AAC Playback" : ["passed"],
        "PROG_MP4_VP9_AAC Seek" : ["passed"]
    }
}
